{
  "routes": [
    {
      "method": "GET",
      "path": "/apontamentos",
      "handler": "apontamento.find",
      "config": {
        "policies": []
      }
    },
    {
      "method": "GET",
      "path": "/apontamentos/count",
      "handler": "apontamento.count",
      "config": {
        "policies": []
      }
    },
    {
      "method": "GET",
      "path": "/apontamentos/:id",
      "handler": "apontamento.findOne",
      "config": {
        "policies": []
      }
    },
    {
      "method": "POST",
      "path": "/apontamentos",
      "handler": "apontamento.create",
      "config": {
        "policies": []
      }
    },
    {
      "method": "PUT",
      "path": "/apontamentos/:id",
      "handler": "apontamento.update",
      "config": {
        "policies": []
      }
    },
    {
      "method": "DELETE",
      "path": "/apontamentos/:id",
      "handler": "apontamento.delete",
      "config": {
        "policies": []
      }
    }
  ]
}
